mock_decorator/__init__.py
mock_decorator-1.0.0.dist-info/LICENSE
mock_decorator-1.0.0.dist-info/METADATA
mock_decorator-1.0.0.dist-info/WHEEL
mock_decorator-1.0.0.dist-info/top_level.txt
mock_decorator-1.0.0.dist-info/RECORD
