Metadata-Version: 2.1
Name: mock-decorator
Version: 1.0.0
Summary: Create a mock object for a Decorator
Author-email: WiredNerd <pbuschmail-github@yahoo.com>
Maintainer-email: WiredNerd <pbuschmail-github@yahoo.com>
License: MIT License
Project-URL: Documentation, https://github.com/WiredNerd/mock-decorator
Project-URL: Homepage, https://github.com/WiredNerd/mock-decorator
Project-URL: Issue Tracker, https://github.com/WiredNerd/mock-decorator/issues
Keywords: test,mock,decorator
Classifier: Programming Language :: Python :: 3
Classifier: License :: OSI Approved :: MIT License
Classifier: Operating System :: OS Independent
Requires-Python: >=3.8
License-File: LICENSE
